pensa/__init__.py
pensa/clusters/__init__.py
pensa/clusters/clustering.py
pensa/clusters/trajectory.py
pensa/clusters/wss.py
pensa/comparison/__init__.py
pensa/comparison/metrics.py
pensa/comparison/projections.py
pensa/comparison/relative_entropy.py
pensa/comparison/statespecific.py
pensa/comparison/statistics.py
pensa/comparison/uncertainty_analysis.py
pensa/comparison/visualization.py
pensa/dimensionality/__init__.py
pensa/dimensionality/lda.py
pensa/dimensionality/pca.py
pensa/dimensionality/qda.py
pensa/dimensionality/tica.py
pensa/dimensionality/visualization.py
pensa/features/__init__.py
pensa/features/atom_features.py
pensa/features/csv_features.py
pensa/features/hbond_features.py
pensa/features/mda_combined.py
pensa/features/mda_distances.py
pensa/features/mda_torsions.py
pensa/features/processing.py
pensa/features/pyemma_features.py
pensa/features/txt_features.py
pensa/features/water_features.py
pensa/preprocessing/__init__.py
pensa/preprocessing/coordinates.py
pensa/preprocessing/density.py
pensa/preprocessing/download.py
pensa/preprocessing/selection.py
pensa/statesinfo/__init__.py
pensa/statesinfo/discrete_states.py
pensa-0.6.0.dist-info/LICENSE
pensa-0.6.0.dist-info/METADATA
pensa-0.6.0.dist-info/WHEEL
pensa-0.6.0.dist-info/top_level.txt
pensa-0.6.0.dist-info/RECORD
